TerraFrame/CelestialTerrestrial.py
TerraFrame/Earth.py
TerraFrame/__init__.py
TerraFrame/Data/EGM2008_to200_TideFree.bin
TerraFrame/Data/TAI_UTC_Delta.txt
TerraFrame/Data/__init__.py
TerraFrame/Data/tab5.2a.txt
TerraFrame/Data/tab5.2b.txt
TerraFrame/Data/tab5.2d.txt
TerraFrame/GravitationModel/GravitationalPotential.py
TerraFrame/GravitationModel/__init__.py
TerraFrame/PrecessionNutation/Arguments.py
TerraFrame/PrecessionNutation/SeriesExpansion.py
TerraFrame/PrecessionNutation/__init__.py
TerraFrame/Utilities/BulletinData.py
TerraFrame/Utilities/Conversions.py
TerraFrame/Utilities/DataFiles.py
TerraFrame/Utilities/Helpers.py
TerraFrame/Utilities/Interpolation.py
TerraFrame/Utilities/TransformationMatrices.py
TerraFrame/Utilities/__init__.py
TerraFrame/Utilities/Time/Deltas.py
TerraFrame/Utilities/Time/JulianDate.py
TerraFrame/Utilities/Time/TimeScales.py
TerraFrame/Utilities/Time/__init__.py
terraframe-0.2.1.dist-info/licenses/LICENSE.txt
terraframe-0.2.1.dist-info/METADATA
terraframe-0.2.1.dist-info/WHEEL
terraframe-0.2.1.dist-info/top_level.txt
terraframe-0.2.1.dist-info/RECORD
