Metadata-Version: 2.4
Name: TerraFrame
Version: 0.2.1
Summary: A library for calculating the orientation of the earth relative to GCRS.
Author-email: Caleb Morrison <cmorrison8191@gmail.com>
Maintainer-email: Caleb Morrison <cmorrison8191@gmail.com>
License: Mozilla Public License
Project-URL: Source, https://github.com/cmorrison31/TerraFrame
Keywords: IAU,Precession,Nutation,Earth,Astronomy,IERS,Transformation,ITRS,GCRS
Classifier: Development Status :: 4 - Beta
Classifier: Intended Audience :: Science/Research
Classifier: Topic :: Scientific/Engineering :: Astronomy
Classifier: License :: OSI Approved :: Mozilla Public License 2.0 (MPL 2.0)
Classifier: Programming Language :: Python :: 3
Classifier: Programming Language :: Python :: 3.12
Classifier: Programming Language :: Python :: 3.13
Classifier: Programming Language :: Python :: 3 :: Only
Requires-Python: >=3.12
License-File: LICENSE.txt
Requires-Dist: numpy
Requires-Dist: platformdirs
Requires-Dist: requests
Provides-Extra: animation
Requires-Dist: manim; extra == "animation"
Provides-Extra: test
Requires-Dist: pytest; extra == "test"
Requires-Dist: pyerfa; extra == "test"
Requires-Dist: astropy; extra == "test"
Dynamic: license-file
